bitccl/__init__.py
bitccl/cli.py
bitccl/compiler.py
bitccl/datatypes.py
bitccl/events.py
bitccl/exceptions.py
bitccl/functions.py
bitccl/logger.py
bitccl/plugins.py
bitccl/state.py
bitccl/utils.py
bitccl/version.py
bitccl/ext/__init__.py
bitccl/ext/http.py
bitccl/ext/sdk.py
bitccl-0.4.3.dist-info/LICENSE
bitccl-0.4.3.dist-info/METADATA
bitccl-0.4.3.dist-info/WHEEL
bitccl-0.4.3.dist-info/entry_points.txt
bitccl-0.4.3.dist-info/top_level.txt
bitccl-0.4.3.dist-info/RECORD
