Metadata-Version: 2.1
Name: bitccl
Version: 0.4.3
Summary: The BitCCL scripting language compiler package
Home-page: https://github.com/bitcart/bitccl
Author: MrNaif2018
Author-email: chuff184@gmail.com
License: MIT
Keywords: bitcart,bitccl,programminglanguage,compiler
Platform: UNKNOWN
Classifier: Development Status :: 3 - Alpha
Classifier: Intended Audience :: Developers
Classifier: License :: OSI Approved :: MIT License
Classifier: Natural Language :: English
Classifier: Programming Language :: Python :: 3
Classifier: Programming Language :: Python :: 3.8
Classifier: Programming Language :: Python :: 3.9
Classifier: Programming Language :: Python :: 3.10
Classifier: Programming Language :: Python :: 3.11
Requires-Python: >=3.8
Requires-Dist: bitcart
Requires-Dist: httpx[http2]
Requires-Dist: Jinja2
Requires-Dist: RestrictedPython
